QLDS_Manager-2.2.5.dist-info/DESCRIPTION.rst
QLDS_Manager-2.2.5.dist-info/METADATA
QLDS_Manager-2.2.5.dist-info/RECORD
QLDS_Manager-2.2.5.dist-info/WHEEL
QLDS_Manager-2.2.5.dist-info/entry_points.txt
QLDS_Manager-2.2.5.dist-info/metadata.json
QLDS_Manager-2.2.5.dist-info/top_level.txt
qldsmanager/__init__.py
qldsmanager/__main__.py
qldsmanager/config
qldsmanager/manager.py
qldsmanager/command/__init__.py
qldsmanager/command/configure.py
qldsmanager/command/default.py
qldsmanager/command/download.py
qldsmanager/command/rcon.py
qldsmanager/command/server.py
qldsmanager/command/supervisor.py
qldsmanager/command/version.py
qldsmanager/util/__init__.py
qldsmanager/util/config.py
qldsmanager/util/filesystem.py
qldsmanager/util/matheval.py
qldsmanager/util/rcon.py
qldsmanager/util/supervisor.py
